	{
		"name": "Platinum",
		"resourceType": "Strategic",
		"revealedBy": "Steel",
		"terrainsCanBeFoundOn": ["Grassland","Plains","Desert","Tundra","Snow","Hill","Marsh"],
		"production": 2,
		"improvement": "Mine",
		"uniques": ["Guaranteed with Strategic Balance resource option",
					"Generated with weight [40] <in [{Featureless} {Tundra}] tiles>",
					"Generated with weight [20] <in [{Featureless} {Snow}] tiles>",
					"Generated with weight [30] <in [{Featureless} {Desert}] tiles>",
					"Generated with weight [29] <in [Hill] tiles>",
					"Minor deposits generated with weight [10] <in [Marsh] tiles> <in tiles without [Hill]>",
					"Minor deposits generated with weight [10] <in [{Jungle} {Hill}] tiles>",
					"Minor deposits generated with weight [20] <in [Forest] tiles>",
					"Minor deposits generated with weight [20] <in [Hill] tiles> <in tiles without [Forest]> <in tiles without [Jungle]>",
					"Minor deposits generated with weight [30] <in [{Featureless} {Grassland}] tiles> <in tiles without [Fresh Water]>",
					"Minor deposits generated with weight [20] <in [{Featureless} {Plains}] tiles>",
					"Minor deposits generated with weight [10] <in [{Featureless} {Desert}] tiles>",
					"Minor deposits generated with weight [10] <in [{Featureless} {Tundra}] tiles>",
					"Minor deposits generated with weight [10] <in [{Featureless} {Snow}] tiles>"],
		"majorDepositAmount": {"sparse": 3, "default": 4, "abundant": 6},
		"minorDepositAmount": {"sparse": 1, "default": 2, "abundant": 3}
	},
	{
		"name": "Volcite",
		"resourceType": "Strategic",
		"revealedBy": "Dynamite",
		"terrainsCanBeFoundOn": ["Desert","Tundra","Snow"],
		"production": 3,
		"improvement": "Mine",
		"uniques": ["Guaranteed with Strategic Balance resource option",
					"Generated with weight [40] <in [{Featureless} {Tundra}] tiles>",
					"Generated with weight [20] <in [{Featureless} {Snow}] tiles>",
					"Generated with weight [30] <in [{Featureless} {Desert}] tiles>",
					"Minor deposits generated with weight [20] <in [Hill] tiles> <in tiles without [Forest]> <in tiles without [Jungle]>",
					"Minor deposits generated with weight [28] <in [{Featureless} {Desert}] tiles> <in tiles without [Fresh Water]>",
					"Minor deposits generated with weight [10] <in [{Featureless} {Desert}] tiles>",
					"Minor deposits generated with weight [10] <in [{Featureless} {Tundra}] tiles>",
					"Minor deposits generated with weight [10] <in [{Featureless} {Snow}] tiles>"],
		"majorDepositAmount": {"sparse": 4, "default": 8, "abundant": 13},
		"minorDepositAmount": {"sparse": 3, "default": 5, "abundant": 9}
	},
